Workbook

Sheet Ventas
A1: Fecha | B1: Hora | C1: Cantidad | D1: Sabor | E1: Método de pago | F1: Precio unitario | G1: Total
A2: 06/05/2026 | B2: 23:54 | C2: 1 | D2: lemon lime | E2: Efectivo | F2: 13 | G2: 13
A3: 07/05/2026 | B3: 00:06 | C3: 1 | D3: sex on the beach | E3: Efectivo | F3: 13 | G3: 13
A4: 07/05/2026 | B4: 00:29 | C4: 1 | D4: lemon lime | E4: Efectivo | F4: 13 | G4: 13

Sheet Catálogo
A1: Sabor | B1: Precio unitario
A2: lemon lime | B2: 13
A3: strawberry banana | B3: 13
A4: mixed berry | B4: 13
A5: strawberry watermelon | B5: 13
A6: pina colada | B6: 13
A7: cherry cola | B7: 13
A8: strawberry kiwi | B8: 13
A9: watermelon ice | B9: 13
A10: sex on the beach | B10: 13
A11: monster mango | B11: 13

Sheet Resumen
A1: Resumen general
A3: Total ventas (€) | B3: =SUM(Ventas!G2:G10000)
A4: Total unidades | B4: =SUM(Ventas!C2:C10000)
A5: Ventas hoy (€) | B5: =SUMIF(Ventas!A2:A10000,TODAY(),Ventas!G2:G10000)
A6: Unidades hoy | B6: =SUMIF(Ventas!A2:A10000,TODAY(),Ventas!C2:C10000)
A8: Por sabor
A9: Sabor | B9: Unidades | C9: Total (€)
A10: lemon lime | B10: =SUMIF(Ventas!D2:D10000,A10,Ventas!C2:C10000) | C10: =SUMIF(Ventas!D2:D10000,A10,Ventas!G2:G10000)
A11: strawberry banana | B11: =SUMIF(Ventas!D2:D10000,A11,Ventas!C2:C10000) | C11: =SUMIF(Ventas!D2:D10000,A11,Ventas!G2:G10000)
A12: mixed berry | B12: =SUMIF(Ventas!D2:D10000,A12,Ventas!C2:C10000) | C12: =SUMIF(Ventas!D2:D10000,A12,Ventas!G2:G10000)
A13: strawberry watermelon | B13: =SUMIF(Ventas!D2:D10000,A13,Ventas!C2:C10000) | C13: =SUMIF(Ventas!D2:D10000,A13,Ventas!G2:G10000)
A14: pina colada | B14: =SUMIF(Ventas!D2:D10000,A14,Ventas!C2:C10000) | C14: =SUMIF(Ventas!D2:D10000,A14,Ventas!G2:G10000)
A15: cherry cola | B15: =SUMIF(Ventas!D2:D10000,A15,Ventas!C2:C10000) | C15: =SUMIF(Ventas!D2:D10000,A15,Ventas!G2:G10000)
A16: strawberry kiwi | B16: =SUMIF(Ventas!D2:D10000,A16,Ventas!C2:C10000) | C16: =SUMIF(Ventas!D2:D10000,A16,Ventas!G2:G10000)
A17: watermelon ice | B17: =SUMIF(Ventas!D2:D10000,A17,Ventas!C2:C10000) | C17: =SUMIF(Ventas!D2:D10000,A17,Ventas!G2:G10000)
A18: sex on the beach | B18: =SUMIF(Ventas!D2:D10000,A18,Ventas!C2:C10000) | C18: =SUMIF(Ventas!D2:D10000,A18,Ventas!G2:G10000)
A19: monster mango | B19: =SUMIF(Ventas!D2:D10000,A19,Ventas!C2:C10000) | C19: =SUMIF(Ventas!D2:D10000,A19,Ventas!G2:G10000)
A22: Por método de pago
A23: Método | B23: Unidades | C23: Total (€)
A24: efectivo | B24: =SUMIF(Ventas!E2:E10000,A24,Ventas!C2:C10000) | C24: =SUMIF(Ventas!E2:E10000,A24,Ventas!G2:G10000)
A25: bizum | B25: =SUMIF(Ventas!E2:E10000,A25,Ventas!C2:C10000) | C25: =SUMIF(Ventas!E2:E10000,A25,Ventas!G2:G10000)
A26: transferencia | B26: =SUMIF(Ventas!E2:E10000,A26,Ventas!C2:C10000) | C26: =SUMIF(Ventas!E2:E10000,A26,Ventas!G2:G10000)
A27: tarjeta | B27: =SUMIF(Ventas!E2:E10000,A27,Ventas!C2:C10000) | C27: =SUMIF(Ventas!E2:E10000,A27,Ventas!G2:G10000)
A28: paypal | B28: =SUMIF(Ventas!E2:E10000,A28,Ventas!C2:C10000) | C28: =SUMIF(Ventas!E2:E10000,A28,Ventas!G2:G10000)
